ai/backend/krunner/centos/__init__.py
ai/backend/krunner/centos/krunner-env.centos7.6.dockerfile
ai/backend/krunner/centos/krunner-env.centos7.6.x86_64.tar.xz
ai/backend/krunner/centos/krunner-python.centos7.6.dockerfile
ai/backend/krunner/centos/krunner-python.centos7.6.txt
ai/backend/krunner/centos/krunner-version.centos7.6.txt
ai/backend/krunner/centos/plugin.py
ai/backend/krunner/centos/requirements.txt
ai/backend/krunner/centos/ttyd_linux.x86_64.bin
ai/backend/krunner/centos/versions.txt
backend.ai_krunner_centos-3.3.0.dist-info/LICENSE
backend.ai_krunner_centos-3.3.0.dist-info/METADATA
backend.ai_krunner_centos-3.3.0.dist-info/WHEEL
backend.ai_krunner_centos-3.3.0.dist-info/entry_points.txt
backend.ai_krunner_centos-3.3.0.dist-info/top_level.txt
backend.ai_krunner_centos-3.3.0.dist-info/RECORD
