Metadata-Version: 2.1
Name: backend.ai-krunner-centos
Version: 3.3.0
Summary: Backend.AI Kernel Runner for CentOS
Home-page: https://backend.ai
Author: Lablup Inc.
Author-email: devops@lablup.com
License: MIT
Platform: UNKNOWN
Requires-Python: >=3.6
Requires-Dist: Click (>=7.1)
Provides-Extra: build
Requires-Dist: wheel (>=0.34.2) ; extra == 'build'
Requires-Dist: twine (~=3.0) ; extra == 'build'
Provides-Extra: ci
Provides-Extra: dev
Requires-Dist: pytest-sugar ; extra == 'dev'
Provides-Extra: test
Requires-Dist: pytest (~=5.4.1) ; extra == 'test'
Requires-Dist: flake8 (>=3.7.9) ; extra == 'test'
Requires-Dist: codecov ; extra == 'test'
